tapo_chatter/__init__.py
tapo_chatter/cli.py
tapo_chatter/config.py
tapo_chatter/device_discovery.py
tapo_chatter/discover.py
tapo_chatter/main.py
tapo_chatter/utils.py
tapo_chatter-0.3.0.dist-info/METADATA
tapo_chatter-0.3.0.dist-info/WHEEL
tapo_chatter-0.3.0.dist-info/entry_points.txt
tapo_chatter-0.3.0.dist-info/licenses/LICENSE
tapo_chatter-0.3.0.dist-info/RECORD
