Metadata-Version: 2.4
Name: tapo_chatter
Version: 0.3.0
Summary: A comprehensive Python application for managing, monitoring, and discovering TP-Link Tapo smart home devices.
Project-URL: Homepage, https://github.com/yourusername/tapo_chatter
Project-URL: Repository, https://github.com/yourusername/tapo_chatter
License: Apache-2.0
License-File: LICENSE
Classifier: License :: OSI Approved :: Apache Software License
Classifier: Operating System :: OS Independent
Classifier: Programming Language :: Python :: 3
Classifier: Programming Language :: Python :: 3.13
Requires-Python: <3.14,>=3.13
Requires-Dist: netifaces>=0.11.0
Requires-Dist: platformdirs>=4.0.0
Requires-Dist: python-dotenv>=1.0.0
Requires-Dist: rich>=13.7.0
Requires-Dist: tapo>=0.2.0
Provides-Extra: dev
Requires-Dist: pytest; extra == 'dev'
Requires-Dist: pytest-cov; extra == 'dev'
Requires-Dist: ruff; extra == 'dev'
